antoine/__init__.py
antoine/app.py
antoine-2.6.dist-info/METADATA
antoine-2.6.dist-info/WHEEL
antoine-2.6.dist-info/entry_points.txt
antoine-2.6.dist-info/top_level.txt
antoine-2.6.dist-info/RECORD
