Metadata-Version: 2.1
Name: antoine
Version: 2.6
Summary: Hiring Antoine is so much fun!
Home-page: https://github.com/monolok/antoine/
Author: Antoine Bertin
Author-email: monolok35@gmail.com
License: MIT
